lenv_py/__init__.py
lenv_py/lenv-wasip1-0.1.7.wasm
lenv_py/main.py
lenv_py-0.1.0.dist-info/METADATA
lenv_py-0.1.0.dist-info/WHEEL
lenv_py-0.1.0.dist-info/entry_points.txt
lenv_py-0.1.0.dist-info/licenses/LICENSE
lenv_py-0.1.0.dist-info/RECORD
