Metadata-Version: 2.3
Name: lenv-py
Version: 0.1.0
Summary: Manage symlinks from a root file to multiple destinations
Author: Ty Hopp
License-File: LICENSE
Requires-Python: >=3.12
Requires-Dist: wasmtime>=25.0.0
